LICENSE
download/__init__.py
download/__main__.py
download/py.typed
python_download-0.0.3.1.dist-info/LICENSE
python_download-0.0.3.1.dist-info/METADATA
python_download-0.0.3.1.dist-info/WHEEL
python_download-0.0.3.1.dist-info/entry_points.txt
python_download-0.0.3.1.dist-info/RECORD
